ipcserver/__init__.py
ipcserver/core/__init__.py
ipcserver/core/app.py
ipcserver/core/client.py
ipcserver/core/config.py
ipcserver/core/forward.py
ipcserver/core/header.py
ipcserver/core/request.py
ipcserver/core/response.py
ipcserver/core/router.py
ipcserver/core/x.py
ipcserver/core/tests/__init__.py
ipcserver/core/tests/test_client.py
ipcserver/core/tests/test_response.py
ipcserver/core/tests/test_router.py
ipcserver/testclient/__init__.py
ipcserver/testclient/annotate.py
ipcserver/testclient/client.py
ipcserver/utils/__init__.py
ipcserver/utils/console.py
ipcserver-0.2.7.dist-info/METADATA
ipcserver-0.2.7.dist-info/WHEEL
ipcserver-0.2.7.dist-info/top_level.txt
ipcserver-0.2.7.dist-info/RECORD
